pushikoo_adapter_testprocesser/__init__.py
pushikoo_adapter_testprocesser/config.py
pushikoo_adapter_testprocesser/main.py
pushikoo_adapter_testprocesser-0.1.2.dist-info/licenses/LICENSE
pushikoo_adapter_testprocesser-0.1.2.dist-info/METADATA
pushikoo_adapter_testprocesser-0.1.2.dist-info/WHEEL
pushikoo_adapter_testprocesser-0.1.2.dist-info/entry_points.txt
pushikoo_adapter_testprocesser-0.1.2.dist-info/top_level.txt
pushikoo_adapter_testprocesser-0.1.2.dist-info/RECORD
