Metadata-Version: 2.4
Name: pushikoo-adapter-testprocesser
Version: 0.1.2
Summary: TestProcesser for pushikoo-adapter development as a template.
Author: Pushikoo
Project-URL: Homepage, https://github.com/Pushikoo/pushikoo-adapter-testprocesser
Classifier: Programming Language :: Python :: 3
Classifier: Operating System :: OS Independent
Requires-Python: >=3.10
License-File: LICENSE
Requires-Dist: pushikoo-interface>=0.3.0
Requires-Dist: requests
Requires-Dist: loguru
Provides-Extra: dev
Requires-Dist: ruff; extra == "dev"
Requires-Dist: pytest; extra == "dev"
Dynamic: license-file
